ccp2_sdk/__init__.py
ccp2_sdk/robot.py
ccp2_sdk-0.1.0.dist-info/LICENSE
ccp2_sdk-0.1.0.dist-info/METADATA
ccp2_sdk-0.1.0.dist-info/WHEEL
ccp2_sdk-0.1.0.dist-info/top_level.txt
ccp2_sdk-0.1.0.dist-info/RECORD
