Metadata-Version: 2.1
Name: ccp2-sdk
Version: 0.1.0
Summary: ccp2 serverless sdk
Home-page: UNKNOWN
Author: cyclone
License: UNKNOWN
Platform: UNKNOWN
License-File: LICENSE
Requires-Dist: requests
